{
    "cipher_type": "monoalphabetic",
    "key_data": {
        "substitution_map": {
            "A": "J",
            "B": "A",
            "C": "H",
            "D": "N",
            "E": "W",
            "F": "Q",
            "G": "L",
            "H": "Z",
            "I": "D",
            "J": "G",
            "K": "Y",
            "L": "P",
            "M": "X",
            "N": "R",
            "\u00d1": "B",
            "O": "I",
            "P": "S",
            "Q": "\u00d1",
            "R": "T",
            "S": "C",
            "T": "O",
            "U": "E",
            "V": "M",
            "W": "U",
            "X": "K",
            "Y": "V",
            "Z": "F"
        },
        "language": "es"
    }
}